csppinet/__init__.py
csppinet/construction.py
csppinet/csppinet.py
csppinet/functions.py
csppinet/network_metrics.py
csppinet-1.2.dist-info/METADATA
csppinet-1.2.dist-info/WHEEL
csppinet-1.2.dist-info/entry_points.txt
csppinet-1.2.dist-info/top_level.txt
csppinet-1.2.dist-info/RECORD
