Metadata-Version: 2.1
Name: csppinet
Version: 1.2
Summary: A Python package for context-specific protein-protein interaction network construction and analysis based on omics data.
Home-page: https://github.com/lmigueel/csppinet/
Author: Luca Miguel de Carvalho
Author-email: lucasmigueel@gmail.com
License: GNU General Public License v3.0
Keywords: bioinformatics,context-specific network,PPI network,interactome,network analysis,omics
Classifier: Development Status :: 3 - Alpha
Classifier: Intended Audience :: Science/Research
Classifier: Natural Language :: English
Classifier: Topic :: Software Development :: Libraries
Classifier: Topic :: Scientific/Engineering :: Bio-Informatics
Classifier: License :: OSI Approved :: GNU General Public License (GPL)
Classifier: Programming Language :: Python :: 3
Requires-Python: >=3
Requires-Dist: numpy
Requires-Dist: pandas
Requires-Dist: networkx (>=2.5)
